elixpy.py
elixpy-0.0.3.dist-info/WHEEL
elixpy-0.0.3.dist-info/METADATA
elixpy-0.0.3.dist-info/RECORD
